mystepup/__Init__.py
mystepup/arth.py
mystepup-0.1.0.dist-info/METADATA
mystepup-0.1.0.dist-info/WHEEL
mystepup-0.1.0.dist-info/top_level.txt
mystepup-0.1.0.dist-info/RECORD
